execute_517/__init__.py
execute_517/__main__.py
execute_517/run.py
execute_517/version.py
execute_517/tests/__init__.py
execute_517-0.2.0.dist-info/LICENSE.rst
execute_517-0.2.0.dist-info/METADATA
execute_517-0.2.0.dist-info/WHEEL
execute_517-0.2.0.dist-info/entry_points.txt
execute_517-0.2.0.dist-info/top_level.txt
execute_517-0.2.0.dist-info/RECORD
