Metadata-Version: 2.1
Name: execute-517
Version: 0.2.0
Summary: Run a command in a PEP 517 env
Home-page: UNKNOWN
Author: Stuart Mumford
Author-email: stuart@cadair.com
License: BSD 3-Clause
Platform: UNKNOWN
Requires-Python: >=3.6
Requires-Dist: build (>=0.3.0)
Provides-Extra: all
Provides-Extra: docs
Requires-Dist: sphinx ; extra == 'docs'
Requires-Dist: sphinx-automodapi ; extra == 'docs'
Provides-Extra: test
Requires-Dist: pytest ; extra == 'test'
Requires-Dist: pytest-doctestplus ; extra == 'test'
Requires-Dist: pytest-cov ; extra == 'test'
